promptledger/__init__.py
promptledger/cli.py
promptledger/core.py
promptledger/db.py
promptledger/ui.py
promptledger-0.2.0.dist-info/METADATA
promptledger-0.2.0.dist-info/WHEEL
promptledger-0.2.0.dist-info/entry_points.txt
promptledger-0.2.0.dist-info/top_level.txt
promptledger-0.2.0.dist-info/RECORD
