Metadata-Version: 2.4
Name: promptledger
Version: 0.2.0
Summary: Local-first prompt version control for developers
Author: PromptLedger Contributors
License: MIT
Project-URL: Homepage, https://github.com/Ertugrulmutlu/promptledger
Project-URL: Repository, https://github.com/Ertugrulmutlu/promptledger
Project-URL: Issues, https://github.com/Ertugrulmutlu/promptledger/issues
Project-URL: CI, https://github.com/Ertugrulmutlu/promptledger/actions
Project-URL: Documentation, https://github.com/Ertugrulmutlu/promptledger#readme
Classifier: Programming Language :: Python :: 3
Classifier: Programming Language :: Python :: 3.10
Classifier: Programming Language :: Python :: 3.11
Classifier: Programming Language :: Python :: 3.12
Classifier: License :: OSI Approved :: MIT License
Classifier: Operating System :: OS Independent
Requires-Python: >=3.10
Provides-Extra: ui
Requires-Dist: streamlit>=1.30; extra == "ui"
Provides-Extra: test
Requires-Dist: pytest; extra == "test"
